bxl/__init__.py
bxl/resource.py
bxl/utils.py
bxl/xnat.py
bxl/config/logconf.ini
bxl-0.3.4.post1.data/scripts/migrate_session.py
bxl-0.3.4.post1.data/scripts/pipeline_launcher.py
bxl-0.3.4.post1.data/scripts/resource_creator.py
bxl-0.3.4.post1.dist-info/LICENSE
bxl-0.3.4.post1.dist-info/METADATA
bxl-0.3.4.post1.dist-info/WHEEL
bxl-0.3.4.post1.dist-info/top_level.txt
bxl-0.3.4.post1.dist-info/RECORD
